makepkg/__init__.py
makepkg/_makepkg.py
makepkg-0.0.4.dist-info/licenses/LICENSE
makepkg-0.0.4.dist-info/METADATA
makepkg-0.0.4.dist-info/WHEEL
makepkg-0.0.4.dist-info/top_level.txt
makepkg-0.0.4.dist-info/RECORD
