Metadata-Version: 2.4
Name: makepkg
Version: 0.0.4
Summary: Python packaging, made simple.
Author-email: Patrick Boateng <patrickboateng@patrickboateng.tech>
License: MIT License
Project-URL: homepage, https://github.com/patrickboateng/makepkg
Classifier: Programming Language :: Python :: 3
Classifier: License :: OSI Approved :: MIT License
Classifier: Operating System :: OS Independent
Classifier: Programming Language :: Python :: 3.10
Classifier: Programming Language :: Python :: 3.11
Classifier: Programming Language :: Python :: 3.12
Requires-Python: >=3.10
License-File: LICENSE
Provides-Extra: dev
Requires-Dist: wheel; extra == "dev"
Requires-Dist: black; extra == "dev"
Requires-Dist: pytest; extra == "dev"
Requires-Dist: mypy; extra == "dev"
Requires-Dist: setuptools; extra == "dev"
Dynamic: license-file
